{
    "headers": {
        "User-Agent": "sentinelhub-py/v3.1.0"
    },
    "payload": null,
    "timestamp": "2021-11-02T17:18:07.265712",
    "url": "https://services.sentinel-hub.com/ogc/wcs/c565d81d-bb72-4556-9150-f5e7215956e2?SERVICE=wcs&WARNINGS=False&MAXCC=5.0&BBOX=21.08427511860191%2C92.19202146232067%2C21.09263458321948%2C92.20118923219735&FORMAT=image%2Ftiff&CRS=EPSG%3A4326&TIME=2020-03-29T04%3A32%3A36%2F2020-03-29T04%3A32%3A36&RESX=10m&RESY=10m&COVERAGE=NDVI&REQUEST=GetCoverage&VERSION=1.1.2"
}